{
    "listings": [
        {
            "pos": 0,
            "is_fiverr_choice": false,
            "seller_name": "xirz_co",
            "seller_country": "PK",
            "seller_level": "LEVEL_TWO",
            "isPro": false,
            "buying_review_rating_count": 293,
            "buying_review_rating": 5,
            "price_i": 100,
            "count": 268,
            "score": 5
        },
        {
            "pos": 1,
            "is_fiverr_choice": false,
            "seller_name": "swift_agency",
            "seller_country": "NG",
            "seller_level": "LEVEL_TWO",
            "isPro": false,
            "buying_review_rating_count": 23,
            "buying_review_rating": 5,
            "price_i": 5,
            "count": 18,
            "score": 5
        },
        {
            "pos": 2,
            "is_fiverr_choice": false,
            "seller_name": "lissanh95",
            "seller_country": "PK",
            "seller_level": "LEVEL_TWO",
            "isPro": false,
            "buying_review_rating_count": 275,
            "buying_review_rating": 5,
            "price_i": 50,
            "count": 180,
            "score": 5
        },
        {
            "pos": 3,
            "is_fiverr_choice": false,
            "seller_name": "sreza007",
            "seller_country": "BD",
            "seller_level": "LEVEL_TWO",
            "isPro": false,
            "buying_review_rating_count": 259,
            "buying_review_rating": 5,
            "price_i": 10,
            "count": 230,
            "score": 5
        },
        {
            "pos": 4,
            "is_fiverr_choice": false,
            "seller_name": "arifa_25",
            "seller_country": "PK",
            "seller_level": "LEVEL_TWO",
            "isPro": false,
            "buying_review_rating_count": 352,
            "buying_review_rating": 5,
            "price_i": 50,
            "count": 173,
            "score": 5
        },
        {
            "pos": 5,
            "is_fiverr_choice": false,
            "seller_name": "katherine_john8",
            "seller_country": "PK",
            "seller_level": "LEVEL_TWO",
            "isPro": false,
            "buying_review_rating_count": 545,
            "buying_review_rating": 4.9,
            "price_i": 90,
            "count": 432,
            "score": 4.9
        },
        {
            "pos": 6,
            "is_fiverr_choice": false,
            "seller_name": "najmulsarker",
            "seller_country": "BD",
            "seller_level": "LEVEL_TWO",
            "isPro": false,
            "buying_review_rating_count": 232,
            "buying_review_rating": 5,
            "price_i": 80,
            "count": 222,
            "score": 5
        },
        {
            "pos": 7,
            "is_fiverr_choice": false,
            "seller_name": "rehanlodhi27",
            "seller_country": "PK",
            "seller_level": "LEVEL_TWO",
            "isPro": false,
            "buying_review_rating_count": 248,
            "buying_review_rating": 5,
            "price_i": 60,
            "count": 179,
            "score": 5
        },
        {
            "pos": 8,
            "is_fiverr_choice": false,
            "seller_name": "ahmadsaeed68",
            "seller_country": "PK",
            "seller_level": "LEVEL_TRS",
            "isPro": true,
            "buying_review_rating_count": 377,
            "buying_review_rating": 5,
            "price_i": 30,
            "count": 279,
            "score": 5
        },
        {
            "pos": 9,
            "is_fiverr_choice": false,
            "seller_name": "emmaexpert621",
            "seller_country": "PK",
            "seller_level": "LEVEL_TWO",
            "isPro": false,
            "buying_review_rating_count": 397,
            "buying_review_rating": 4.9,
            "price_i": 10,
            "count": 328,
            "score": 4.9
        },
        {
            "pos": 10,
            "is_fiverr_choice": false,
            "seller_name": "webdeventh",
            "seller_country": "PK",
            "seller_level": "LEVEL_TWO",
            "isPro": false,
            "buying_review_rating_count": 135,
            "buying_review_rating": 4.9,
            "price_i": 15,
            "count": 101,
            "score": 4.9
        },
        {
            "pos": 11,
            "is_fiverr_choice": false,
            "seller_name": "urwa_pk",
            "seller_country": "PK",
            "seller_level": "LEVEL_TWO",
            "isPro": false,
            "buying_review_rating_count": 1291,
            "buying_review_rating": 4.9,
            "price_i": 60,
            "count": 899,
            "score": 4.9
        },
        {
            "pos": 12,
            "is_fiverr_choice": false,
            "seller_name": "sany_majumder1",
            "seller_country": "BD",
            "seller_level": "LEVEL_TWO",
            "isPro": false,
            "buying_review_rating_count": 512,
            "buying_review_rating": 5,
            "price_i": 20,
            "count": 434,
            "score": 5
        },
        {
            "pos": 13,
            "is_fiverr_choice": false,
            "seller_name": "amazon_exprt30",
            "seller_country": "PK",
            "seller_level": "LEVEL_TWO",
            "isPro": false,
            "buying_review_rating_count": 20,
            "buying_review_rating": 4.9,
            "price_i": 10,
            "count": 13,
            "score": 4.9
        },
        {
            "pos": 14,
            "is_fiverr_choice": false,
            "seller_name": "fmchisti",
            "seller_country": "BD",
            "seller_level": "LEVEL_TWO",
            "isPro": false,
            "buying_review_rating_count": 114,
            "buying_review_rating": 5,
            "price_i": 45,
            "count": 81,
            "score": 5
        },
        {
            "pos": 15,
            "is_fiverr_choice": false,
            "seller_name": "tayab_pabel",
            "seller_country": "BD",
            "seller_level": "LEVEL_TWO",
            "isPro": false,
            "buying_review_rating_count": 49,
            "buying_review_rating": 5,
            "price_i": 100,
            "count": 28,
            "score": 5
        },
        {
            "pos": 16,
            "is_fiverr_choice": false,
            "seller_name": "wpkashif",
            "seller_country": "PK",
            "seller_level": "LEVEL_TWO",
            "isPro": false,
            "buying_review_rating_count": 112,
            "buying_review_rating": 4.9,
            "price_i": 25,
            "count": 90,
            "score": 4.9
        },
        {
            "pos": 17,
            "is_fiverr_choice": false,
            "seller_name": "mr_kamranali",
            "seller_country": "PK",
            "seller_level": "LEVEL_TWO",
            "isPro": false,
            "buying_review_rating_count": 1482,
            "buying_review_rating": 4.9,
            "price_i": 20,
            "count": 1014,
            "score": 4.9
        },
        {
            "pos": 18,
            "is_fiverr_choice": false,
            "seller_name": "alarenov",
            "seller_country": "ID",
            "seller_level": "LEVEL_TWO",
            "isPro": false,
            "buying_review_rating_count": 89,
            "buying_review_rating": 5,
            "price_i": 90,
            "count": 48,
            "score": 5
        },
        {
            "pos": 19,
            "is_fiverr_choice": false,
            "seller_name": "webnayon",
            "seller_country": "BD",
            "seller_level": "LEVEL_TWO",
            "isPro": false,
            "buying_review_rating_count": 193,
            "buying_review_rating": 5,
            "price_i": 15,
            "count": 163,
            "score": 5
        },
        {
            "pos": 20,
            "is_fiverr_choice": false,
            "seller_name": "wordpress_play",
            "seller_country": "PK",
            "seller_level": "LEVEL_TWO",
            "isPro": false,
            "buying_review_rating_count": 1896,
            "buying_review_rating": 4.9,
            "price_i": 10,
            "count": 1496,
            "score": 4.9
        },
        {
            "pos": 21,
            "is_fiverr_choice": false,
            "seller_name": "junaid710",
            "seller_country": "PK",
            "seller_level": "LEVEL_TRS",
            "isPro": false,
            "buying_review_rating_count": 935,
            "buying_review_rating": 4.8,
            "price_i": 50,
            "count": 572,
            "score": 4.8
        },
        {
            "pos": 22,
            "is_fiverr_choice": false,
            "seller_name": "salv997",
            "seller_country": "IT",
            "seller_level": "LEVEL_TWO",
            "isPro": false,
            "buying_review_rating_count": 35,
            "buying_review_rating": 5,
            "price_i": 75,
            "count": 30,
            "score": 5
        },
        {
            "pos": 23,
            "is_fiverr_choice": false,
            "seller_name": "mr_moaz",
            "seller_country": "PK",
            "seller_level": "LEVEL_TWO",
            "isPro": false,
            "buying_review_rating_count": 417,
            "buying_review_rating": 5,
            "price_i": 10,
            "count": 336,
            "score": 5
        },
        {
            "pos": 24,
            "is_fiverr_choice": false,
            "seller_name": "aarman_shohan",
            "seller_country": "BD",
            "seller_level": "LEVEL_TWO",
            "isPro": false,
            "buying_review_rating_count": 276,
            "buying_review_rating": 5,
            "price_i": 30,
            "count": 225,
            "score": 5
        },
        {
            "pos": 25,
            "is_fiverr_choice": false,
            "seller_name": "mansuralam",
            "seller_country": "BD",
            "seller_level": "LEVEL_TRS",
            "isPro": false,
            "buying_review_rating_count": 260,
            "buying_review_rating": 4.9,
            "price_i": 100,
            "count": 175,
            "score": 4.9
        },
        {
            "pos": 26,
            "is_fiverr_choice": false,
            "seller_name": "husnaintariq097",
            "seller_country": "PK",
            "seller_level": "LEVEL_TWO",
            "isPro": false,
            "buying_review_rating_count": 440,
            "buying_review_rating": 4.9,
            "price_i": 30,
            "count": 301,
            "score": 4.9
        },
        {
            "pos": 27,
            "is_fiverr_choice": false,
            "seller_name": "dev_rahul_das",
            "seller_country": "BD",
            "seller_level": "LEVEL_TWO",
            "isPro": false,
            "buying_review_rating_count": 788,
            "buying_review_rating": 5,
            "price_i": 15,
            "count": 662,
            "score": 5
        },
        {
            "pos": 28,
            "is_fiverr_choice": false,
            "seller_name": "awais_javed8",
            "seller_country": "CA",
            "seller_level": "LEVEL_TRS",
            "isPro": false,
            "buying_review_rating_count": 4563,
            "buying_review_rating": 4.9,
            "price_i": 45,
            "count": 3190,
            "score": 4.9
        },
        {
            "pos": 29,
            "is_fiverr_choice": false,
            "seller_name": "awaismanzoor950",
            "seller_country": "PK",
            "seller_level": "LEVEL_TWO",
            "isPro": false,
            "buying_review_rating_count": 330,
            "buying_review_rating": 4.9,
            "price_i": 40,
            "count": 245,
            "score": 4.9
        },
        {
            "pos": 30,
            "is_fiverr_choice": false,
            "seller_name": "wordpressnow",
            "seller_country": "PK",
            "seller_level": "LEVEL_TRS",
            "isPro": false,
            "buying_review_rating_count": 1231,
            "buying_review_rating": 5,
            "price_i": 5,
            "count": 795,
            "score": 5
        },
        {
            "pos": 31,
            "is_fiverr_choice": false,
            "seller_name": "jasim_shopify",
            "seller_country": "PK",
            "seller_level": "LEVEL_TWO",
            "isPro": false,
            "buying_review_rating_count": 450,
            "buying_review_rating": 5,
            "price_i": 20,
            "count": 386,
            "score": 5
        },
        {
            "pos": 32,
            "is_fiverr_choice": false,
            "seller_name": "tiaanrich",
            "seller_country": "ZA",
            "seller_level": "LEVEL_TRS",
            "isPro": true,
            "buying_review_rating_count": 786,
            "buying_review_rating": 4.9,
            "price_i": 80,
            "count": 568,
            "score": 4.9
        },
        {
            "pos": 33,
            "is_fiverr_choice": false,
            "seller_name": "faizankhan_246",
            "seller_country": "PK",
            "seller_level": "LEVEL_TWO",
            "isPro": false,
            "buying_review_rating_count": 609,
            "buying_review_rating": 4.9,
            "price_i": 70,
            "count": 362,
            "score": 4.9
        },
        {
            "pos": 34,
            "is_fiverr_choice": false,
            "seller_name": "jawadnagi",
            "seller_country": "PK",
            "seller_level": "LEVEL_TWO",
            "isPro": false,
            "buying_review_rating_count": 903,
            "buying_review_rating": 5,
            "price_i": 15,
            "count": 637,
            "score": 5
        },
        {
            "pos": 35,
            "is_fiverr_choice": false,
            "seller_name": "shoaib_web",
            "seller_country": "PK",
            "seller_level": "LEVEL_TRS",
            "isPro": false,
            "buying_review_rating_count": 30,
            "buying_review_rating": 4.9,
            "price_i": 85,
            "count": 21,
            "score": 4.9
        },
        {
            "pos": 36,
            "is_fiverr_choice": false,
            "seller_name": "girdharidev",
            "seller_country": "IN",
            "seller_level": "LEVEL_TWO",
            "isPro": false,
            "buying_review_rating_count": 210,
            "buying_review_rating": 4.9,
            "price_i": 35,
            "count": 109,
            "score": 4.9
        },
        {
            "pos": 37,
            "is_fiverr_choice": false,
            "seller_name": "faizan_rajputt",
            "seller_country": "PK",
            "seller_level": "LEVEL_TWO",
            "isPro": false,
            "buying_review_rating_count": 47,
            "buying_review_rating": 5,
            "price_i": 35,
            "count": 46,
            "score": 5
        },
        {
            "pos": 38,
            "is_fiverr_choice": false,
            "seller_name": "saifeshanto01",
            "seller_country": "BD",
            "seller_level": "LEVEL_TWO",
            "isPro": false,
            "buying_review_rating_count": 179,
            "buying_review_rating": 5,
            "price_i": 10,
            "count": 140,
            "score": 5
        },
        {
            "pos": 39,
            "is_fiverr_choice": false,
            "seller_name": "jamedeveloper",
            "seller_country": "GB",
            "seller_level": "LEVEL_TWO",
            "isPro": false,
            "buying_review_rating_count": 2222,
            "buying_review_rating": 4.9,
            "price_i": 25,
            "count": 1336,
            "score": 4.9
        },
        {
            "pos": 40,
            "is_fiverr_choice": false,
            "seller_name": "umair_aly28",
            "seller_country": "PK",
            "seller_level": "LEVEL_TWO",
            "isPro": false,
            "buying_review_rating_count": 800,
            "buying_review_rating": 5,
            "price_i": 20,
            "count": 590,
            "score": 5
        },
        {
            "pos": 41,
            "is_fiverr_choice": false,
            "seller_name": "sazzad_29",
            "seller_country": "BD",
            "seller_level": "LEVEL_TWO",
            "isPro": false,
            "buying_review_rating_count": 46,
            "buying_review_rating": 4.9,
            "price_i": 15,
            "count": 44,
            "score": 4.9
        },
        {
            "pos": 42,
            "is_fiverr_choice": false,
            "seller_name": "adeebhat",
            "seller_country": "IN",
            "seller_level": "LEVEL_TWO",
            "isPro": false,
            "buying_review_rating_count": 1014,
            "buying_review_rating": 4.9,
            "price_i": 10,
            "count": 796,
            "score": 4.9
        },
        {
            "pos": 43,
            "is_fiverr_choice": false,
            "seller_name": "hashammalik1",
            "seller_country": "PK",
            "seller_level": "LEVEL_TWO",
            "isPro": false,
            "buying_review_rating_count": 220,
            "buying_review_rating": 4.9,
            "price_i": 80,
            "count": 203,
            "score": 4.9
        },
        {
            "pos": 44,
            "is_fiverr_choice": false,
            "seller_name": "khurramiii",
            "seller_country": "PK",
            "seller_level": "LEVEL_TRS",
            "isPro": false,
            "buying_review_rating_count": 1906,
            "buying_review_rating": 5,
            "price_i": 30,
            "count": 1379,
            "score": 5
        },
        {
            "pos": 45,
            "is_fiverr_choice": false,
            "seller_name": "itsubaid",
            "seller_country": "PK",
            "seller_level": "LEVEL_ONE",
            "isPro": false,
            "buying_review_rating_count": 1552,
            "buying_review_rating": 5,
            "price_i": 50,
            "count": 925,
            "score": 5
        },
        {
            "pos": 46,
            "is_fiverr_choice": false,
            "seller_name": "dereksiu",
            "seller_country": "AU",
            "seller_level": "LEVEL_TRS",
            "isPro": true,
            "buying_review_rating_count": 197,
            "buying_review_rating": 5,
            "price_i": 70,
            "count": 127,
            "score": 5
        },
        {
            "pos": 47,
            "is_fiverr_choice": false,
            "seller_name": "alihyder009",
            "seller_country": "PK",
            "seller_level": "LEVEL_TWO",
            "isPro": false,
            "buying_review_rating_count": 3,
            "buying_review_rating": 5,
            "price_i": 55,
            "count": 3,
            "score": 5
        }
    ]
}